{"authors": [], "date_download": "2024-02-05 15:44:47", "date_modify": "None", "date_publish": "2023-11-06 17:29:13", "description": "Israel started bombing the Palestinian territory after coming under attack from Hamas on 7 October.", "filename": "https%3A%2F%2Fwww.bbc.co.uk%2Fnews%2Fworld-middle-east-67332684%3Fat_medium%3DRSS%26at_campaign%3DKARANGA.json", "image_url": "https://ichef.bbci.co.uk/news/1024/branded_news/8A36/production/_131628353_mediaitem131628349.jpg", "language": "en", "localpath": null, "maintext": "The heads of organisations including Unicef, the WHO and the World Food Programme - as well as charities such as Save the Children - have described the \"horrific\" loss of life on both sides. They have also released a statement to demand the unconditional release of the hostages taken by Hamas during its 7 October attacks.", "source_domain": "www.bbc.co.uk", "text": null, "title": "Israel Gaza war: Hamas-run health ministry says Gaza death toll passes 10,000", "title_page": null, "title_rss": null, "url": "https://www.bbc.co.uk/news/world-middle-east-67332684?at_medium=RSS&at_campaign=KARANGA"}